pytanga/__init__.py
pytanga/components/AbstractComponent.py
pytanga/components/__init__.py
pytanga/components/config.py
pytanga/components/filter.py
pytanga/components/filterComponent.py
pytanga/components/rpc.py
pytanga/components/Cisco/__init__.py
pytanga/components/Cisco/xe/__init__.py
pytanga/components/Cisco/xe/checkpoint.py
pytanga/components/Cisco/xe/native.py
pytanga/components/Cisco/xe/rollback.py
pytanga/components/Cisco/xe/router.py
pytanga/components/Cisco/xe/save_config.py
pytanga/components/Cisco/xe/saveconfig.py
pytanga/components/Cisco/xe/bgp/__init__.py
pytanga/components/Cisco/xe/bgp/addressFamilyIPv4Unicast.py
pytanga/components/Cisco/xe/bgp/addressFamilyType.py
pytanga/components/Cisco/xe/bgp/addressFamilyVRF.py
pytanga/components/Cisco/xe/bgp/addressfamilies.py
pytanga/components/Cisco/xe/bgp/bgp.py
pytanga/components/Cisco/xe/bgp/neighbor.py
pytanga/components/Cisco/xe/bgp/neighborAdvertiseMap.py
pytanga/components/Cisco/xe/bgp/neighborAdvertiseMaps.py
pytanga/components/Cisco/xe/bgp/neighborDistributeList.py
pytanga/components/Cisco/xe/bgp/neighborPrefixList.py
pytanga/components/Cisco/xe/bgp/neighborRouteMap.py
pytanga/components/Cisco/xe/bgp/network.py
pytanga/components/Cisco/xe/bgp/peergroup.py
pytanga/components/Cisco/xe/ip/__init__.py
pytanga/components/Cisco/xe/ip/ip.py
pytanga/components/Cisco/xe/ip/prefix.py
pytanga/components/Cisco/xe/ip/prefixlist.py
pytanga/components/Cisco/xe/ip/prefixlists.py
pytanga/components/Cisco/xe/ip/routemap.py
pytanga/components/Cisco/xe/ip/routemapentry.py
pytanga/components/Cisco/xe/ospf/__init__.py
pytanga/components/Cisco/xe/ospf/area.py
pytanga/components/Cisco/xe/ospf/network.py
pytanga/components/Cisco/xe/ospf/ospf.py
pytanga/components/Cisco/xr/__init__.py
pytanga/components/OpenConfig/__init__.py
pytanga/components/OpenConfig/interfaces/__init__.py
pytanga/components/OpenConfig/interfaces/ethernet.py
pytanga/components/OpenConfig/interfaces/interface.py
pytanga-1.0.9.dist-info/LICENSE
pytanga-1.0.9.dist-info/METADATA
pytanga-1.0.9.dist-info/WHEEL
pytanga-1.0.9.dist-info/top_level.txt
pytanga-1.0.9.dist-info/RECORD
