Metadata-Version: 2.1
Name: pytanga
Version: 1.0.9
Summary: Python Library to simplify NETCONF payload creation
Home-page: https://github.com/renatoalmeidaoliveira/Pytanga
Author: Renato Almeida de Oliveira
Author-email: renato.almeida.oliveira@gmail.com
License: UNKNOWN
Project-URL: Documentation, https://pytanga.renatooliveira.eng.br
Platform: UNKNOWN
Classifier: Programming Language :: Python :: 3
Classifier: License :: OSI Approved :: MIT License
Classifier: Operating System :: OS Independent
Requires-Python: >=3.6
